Metadata-Version: 1.0
Name: tst-distributions
Version: 0.1
Summary: Gaussian distributions
Home-page: UNKNOWN
Author: Jubert Roldan
Author-email: jubertroldan@gmail.com
License: UNKNOWN
Platform: UNKNOWN
